CHANGELOG
README.html
README.org
nalude/__init__.py
nalude/extra.py
nalude/nalude.py
nalude/types.py
poetry.lock
nalude-0.3.0.dist-info/LICENSE
nalude-0.3.0.dist-info/WHEEL
nalude-0.3.0.dist-info/METADATA
nalude-0.3.0.dist-info/RECORD
